[{
  "_id": {
    "$oid": "68f8dc286207c5c70a8be116"
  },
  "name": {
    "en": "HTML",
    "ar": "HTML"
  },
  "category": "frontend",
  "level": 50,
  "icon": "https://cdn.jsdelivr.net/gh/devicons/devicon@latest/icons/html5/html5-original.svg",
  "color": "#3B82F6",
  "order": 0,
  "createdAt": {
    "$date": "2025-10-22T13:29:12.979Z"
  },
  "updatedAt": {
    "$date": "2025-10-22T13:29:12.979Z"
  },
  "__v": 0
},
{
  "_id": {
    "$oid": "68f8dc4f6207c5c70a8be11a"
  },
  "name": {
    "en": "CSS",
    "ar": "CSS"
  },
  "category": "frontend",
  "level": 50,
  "icon": "https://cdn.jsdelivr.net/gh/devicons/devicon@latest/icons/css3/css3-original.svg",
  "color": "#3B82F6",
  "order": 0,
  "createdAt": {
    "$date": "2025-10-22T13:29:51.303Z"
  },
  "updatedAt": {
    "$date": "2025-10-22T13:29:51.303Z"
  },
  "__v": 0
},
{
  "_id": {
    "$oid": "68f8dc7b6207c5c70a8be11e"
  },
  "name": {
    "en": "Java Script",
    "ar": "Java Script"
  },
  "category": "frontend",
  "level": 50,
  "icon": "https://cdn.jsdelivr.net/gh/devicons/devicon@latest/icons/javascript/javascript-original.svg",
  "color": "#3B82F6",
  "order": 0,
  "createdAt": {
    "$date": "2025-10-22T13:30:35.283Z"
  },
  "updatedAt": {
    "$date": "2025-10-22T13:30:35.283Z"
  },
  "__v": 0
},
{
  "_id": {
    "$oid": "68f8e16f6207c5c70a8be12e"
  },
  "name": {
    "en": "Node.JS",
    "ar": "Node.JS"
  },
  "category": "backend",
  "level": 50,
  "icon": "https://cdn.jsdelivr.net/gh/devicons/devicon@latest/icons/nodejs/nodejs-original-wordmark.svg",
  "color": "#3B82F6",
  "order": 0,
  "createdAt": {
    "$date": "2025-10-22T13:51:43.537Z"
  },
  "updatedAt": {
    "$date": "2025-10-22T13:51:43.537Z"
  },
  "__v": 0
},
{
  "_id": {
    "$oid": "68f8e1956207c5c70a8be132"
  },
  "name": {
    "en": "Express.JS",
    "ar": "Express.JS"
  },
  "category": "backend",
  "level": 50,
  "icon": "https://cdn.jsdelivr.net/gh/devicons/devicon@latest/icons/express/express-original-wordmark.svg",
  "color": "#3B82F6",
  "order": 0,
  "createdAt": {
    "$date": "2025-10-22T13:52:21.431Z"
  },
  "updatedAt": {
    "$date": "2025-10-22T13:52:21.431Z"
  },
  "__v": 0
},
{
  "_id": {
    "$oid": "68f8e1b46207c5c70a8be136"
  },
  "name": {
    "en": "MongoDB",
    "ar": "MongoDB"
  },
  "category": "database",
  "level": 50,
  "icon": "https://cdn.jsdelivr.net/gh/devicons/devicon@latest/icons/mongodb/mongodb-original-wordmark.svg",
  "color": "#3B82F6",
  "order": 0,
  "createdAt": {
    "$date": "2025-10-22T13:52:52.736Z"
  },
  "updatedAt": {
    "$date": "2025-10-22T13:52:52.736Z"
  },
  "__v": 0
},
{
  "_id": {
    "$oid": "68fb5c5d9999c49344556450"
  },
  "name": {
    "en": "Docker",
    "ar": "Docker"
  },
  "category": "devops",
  "level": 50,
  "icon": "https://cdn.jsdelivr.net/gh/devicons/devicon@latest/icons/docker/docker-original.svg",
  "color": "#3B82F6",
  "order": 0,
  "createdAt": {
    "$date": "2025-10-24T11:00:45.557Z"
  },
  "updatedAt": {
    "$date": "2025-10-24T11:02:37.673Z"
  },
  "__v": 0
},
{
  "_id": {
    "$oid": "68fb5c859999c49344556454"
  },
  "name": {
    "en": "Git",
    "ar": "Git"
  },
  "category": "devops",
  "level": 50,
  "icon": "https://cdn.jsdelivr.net/gh/devicons/devicon@latest/icons/git/git-original-wordmark.svg",
  "color": "#3B82F6",
  "order": 0,
  "createdAt": {
    "$date": "2025-10-24T11:01:25.106Z"
  },
  "updatedAt": {
    "$date": "2025-10-24T11:02:31.046Z"
  },
  "__v": 0
},
{
  "_id": {
    "$oid": "68fb5d319999c49344556460"
  },
  "name": {
    "en": "GraphQL",
    "ar": "GraphQL"
  },
  "category": "backend",
  "level": 50,
  "icon": "https://cdn.jsdelivr.net/gh/devicons/devicon@latest/icons/graphql/graphql-plain-wordmark.svg",
  "color": "#3B82F6",
  "order": 0,
  "createdAt": {
    "$date": "2025-10-24T11:04:17.011Z"
  },
  "updatedAt": {
    "$date": "2025-10-24T11:04:17.011Z"
  },
  "__v": 0
},
{
  "_id": {
    "$oid": "68fb5da19999c4934455646a"
  },
  "name": {
    "en": "NEXT.js",
    "ar": "NEXT.js"
  },
  "category": "frontend",
  "level": 50,
  "icon": "https://cdn.jsdelivr.net/gh/devicons/devicon@latest/icons/nextjs/nextjs-original-wordmark.svg",
  "color": "#3B82F6",
  "order": 0,
  "createdAt": {
    "$date": "2025-10-24T11:06:09.340Z"
  },
  "updatedAt": {
    "$date": "2025-10-24T11:06:09.340Z"
  },
  "__v": 0
},
{
  "_id": {
    "$oid": "68fb88fe3c66855b96cd2e18"
  },
  "name": {
    "en": "React.js",
    "ar": "React.js"
  },
  "category": "frontend",
  "level": 50,
  "icon": "https://cdn.jsdelivr.net/gh/devicons/devicon@latest/icons/react/react-original.svg",
  "color": "#3B82F6",
  "order": 0,
  "createdAt": {
    "$date": "2025-10-24T14:11:10.604Z"
  },
  "updatedAt": {
    "$date": "2025-10-24T14:11:10.604Z"
  },
  "__v": 0
}]